{"科目名":"宗　教　学　Ⅱ","講義名":"宗教学Ⅱ","受講可能学科":"全学部・全学科","担当研究室":"教養文化・学芸員","担当教員":"蓮池　隆広","分野":"文化総合Ⅰ類","対象学年":"1年,2年,3年,4年","科目群":"教養文化Ⅰ類","キャンパス":"鷹の台","開講期間":"後期 2021/09/06-2021/12/18","曜日・時限":"火３","授業形態":"講義","単位数":"2.0","履修条件":"150人","授業概要・カリキュラム上の位置づけ":"現代の日本では、多くの人が自らを「無宗教」と考える一方で、日常生活に根づいた儀礼や慣習など、広い意味での「宗教的」行動には何らか関わっていることが多い。また、グローバル化が進む社会のなかで、他者の宗教と向き合う必要性もますます高まっている。本授業では、死と死者をめぐる問題を宗教との関わりで見ていくということと、近現代の社会と宗教との関係を見ていくということの二つを大きな柱とする。歴史をたどり、世界各地の状況に目を向けながら、宗教学の概念と知見を用いて、複数の視角からこの二つのテーマを考えていく。","授業方法":"オンデマンド（非同期）とリアルタイム（同時双方向）の併用：Teamsを使用したオンライン授業を基本とし、一部、Zoomによるリアルタイム型のオンライン授業を取り入れます。","到達目標":"①宗教学の基礎概念と方法を理解する。②現代社会の問題を考えるための多様な視角を獲得する。③自らの立ち位置を問い直しつつ、他者の宗教に知的に向き合う。④ディプロマポリシーにある「総合的判断力と批判力」を高める。","ディプロマポリシーとの関連":"https://www.musabi.ac.jp/wp-content/uploads/2021/05/CurriculumMap_la1.pdf","授業計画・課題に対するフィードバック":"Teamsを用い、毎回、文章による講義資料を配布します。それを読み、その回の課題に取り組み、提出してもらいます。Teamsの機能を使用して、提出課題への全体的なフィードバックを行うとともに、個別の質問にも対応します。また、授業時間の一部を使って、Zoomによる補足説明や質疑応答を取り入れていく予定です。学期末にレポートを課します。第1回　イントロダクション第2回　死生学と宗教学第3回　ケアと宗教第4回　他界観①第5回　他界観②第6回　葬送儀礼と墓第7回　慰霊と追悼第8回　近代社会と宗教①第9回　近代社会と宗教②第10回　国民国家と宗教①第11回　国民国家と宗教②第12回　ジェンダーと宗教第13回　宗教と紛争・暴力第14回　宗教と共生第15回　まとめ","履修上の留意点":"Teamsを使用したオンデマンド（非同期）型を基本とし、その回の課題提出をもって出席とします。定員１５０人とし、それを超えた場合は抽選となります。","準備学習内容・時間の目安":"問題関心と知識・思考を深めていくためには、自ら書物を読むことが不可欠である。参考図書は授業時に紹介するので、自分の関心に沿って掘り下げていく。（30分）","成績評価の方法":"毎回のオンライン授業の課題60%、レポート40%","テキスト":"なし","参考文献(作品）等":"参考文献は授業時に紹介する","教員との連絡方法（オフィスアワー）":"講義内容に関する質問等は、毎授業時に受け付ける。"}