{"科目名":"International Communication Ⅰ","講義名":"International Communication ⅠC","サブタイトル":"Acquiring  English knowledge and skills through art.","担当研究室":"クリエイティブイノベーション学科","担当教員":"清水　由布紀","分野":"専門基礎科目","対象学年":"3年","科目群":"専門基礎（必修）","キャンパス":"","開講期間":"第1ターム 2021/04/12-2021/06/05","曜日・時限":"火５","授業形態":"演習","単位数":"1.0","授業概要・カリキュラム上の位置づけ":"これまで身に着けた英語力を生かし、グローバルに活躍するためのコミュニケーション能力を向上させることを目指す。美術・デザインのテキストや映像資料を通じ、英語の表現に慣れ親しみ、プレゼンテーションをすることで、自らを発信する力を養う。この目標を達成するために以下の活動を行う。1. 英語テキストを通じた文法事項・英単語、英語テキストの読み方の修得2. 英語を用いた自分の考え・主張の発信これらの活動を通じ、学生が英語テキストの概要を正しく把握し、英語で自身の意見を効果的に他者に伝えることできるようになることを最終目標とする。","授業方法":"対面で授業を行う予定。学生の発言が求められる。","到達目標":"1. 語彙力の増強や英語の表現の拡大を図る。2. 文法や英文の論理的構造の特徴を理解する。3. 多角的な視点を踏まえ、自らの考えを効果的に英語でプレゼンテーションする力を養う。","ディプロマポリシーとの関連":"https://www.musabi.ac.jp/wp-content/uploads/2021/05/CurriculumMap_ci.pdf","授業計画・課題に対するフィードバック":"第１回　イントロダクション第２回　A Boutique Handbag Brand Inspired by Both Europe and Asia第３回　Introducing Yuni Yunan第４回　The Great Wave in Twenty-first CenturyEuro-American Culture①第５回　The Great Wave in Twenty-first CenturyEuro-American Culture②第６回　The Great Wave in Twenty-first CenturyEuro-American Culture③第７回　How to spread your culture to the world第８回　プレゼンテーション発表","履修上の留意点":"辞書を持参すること。","準備学習内容・時間の目安":"講義前に指示されたテキストの予習を行うこと。また最終プレゼンテーションの準備も進めておくこと。","成績評価の方法":"授業の貢献度、課題、プレゼンテーション。","テキスト":"授業内で適宜配布する。","テキストISBN番号":"特になし","参考文献(作品）等":"Hokusai's Great Wave: Biography of a Global Icon( University of Hawaii Press, 2015)","教員との連絡方法（オフィスアワー）":"講義内容に関する質問等は、授業の前後でも、いつでも(Teamsで)受け付ける。"}