{"科目名":"自然科学Ⅰ","講義名":"自然科学Ⅰ","サブタイトル":"（物理、サイエンス・アートを中心に）","受講可能学科":"全学部・全学科","担当研究室":"教養文化・学芸員","担当教員":"宮原　ひろ子","分野":"文化総合Ⅰ類","対象学年":"1年,2年,3年,4年","科目群":"教養文化Ⅰ類","キャンパス":"鷹の台","開講期間":"前期 2021/04/12-2021/07/10","曜日・時限":"木４","授業形態":"講義","単位数":"2.0","履修条件":"150人","授業概要・カリキュラム上の位置づけ":"私たちの住む世界がどのような物理法則に支配されているのか、その概要を学びます。授業では、サイエンス・アートについても紹介します。「自然科学Ⅰ」では、主に物理学を中心に学習します。「自然科学Ⅱ」では、地球史を中心に学習します。ⅠとⅡは完全に独立していますので、どちらか片方だけを履修することもできます。","授業方法":"Teamsによるオンライン授業（オンデマンド型）","到達目標":"① 自然現象を観察する力を身につける② 物理法則について理解を深めることを目標とします。また、③ 科学的に正しい情報を収集する力を身につけることも目標とします。","ディプロマポリシーとの関連":"https://www.musabi.ac.jp/wp-content/uploads/2021/05/CurriculumMap_la1.pdf","授業計画・課題に対するフィードバック":"主に講義映像の視聴により学習を進めていただきます。Microsoft Formsにより質問を受け付けます。翌週に解説します。第1回 授業のガイダンス　－物理学とは何か第2回 科学とは何か①第3回 科学とは何か②第4回 ニュートンの運動の法則第5回 エネルギー保存の法則第6回 流体力学第7回 温度と熱第8回 光と音波第9回 電気と磁気第10回 素粒子の世界第11回 アインシュタインの特殊相対性理論第12回 シュレディンガーの猫第13回 自然現象の物理①第14回 自然現象の物理②第15回 まとめ","履修上の留意点":"PC、タブレット、スマートフォン等を使用して、講義映像を視聴していただきます。人数制限を行っています。定員を超えた場合は抽選となります。","準備学習内容・時間の目安":"日頃から科学技術に関するニュースや本を読むこと。また、興味を持ったサイエンスアートについて、その原理をインターネット等で調べること。","成績評価の方法":"平常点および期末レポートにより総合的に評価します。","テキスト":"なし"}