{"科目名":"卒　業　制　作","講義名":"卒業制作","サブタイトル":"卒業制作テキスタイル21～29授業週 〈6単位 実技〉","受講可能学科":"造形学部・工芸工業デザイン学科","担当研究室":"工芸工業デザイン学科","担当教員":"高橋　理子、徂徠　友香子、片平　隆行、竹内　優美、後藤　大樹、シミズダニ　ヤスノブ、光主　あゆみ","分野":"卒業制作","対象学年":"4年","科目群":"卒業制作","キャンパス":"鷹の台","開講期間":"５.６.７期 2021/10/04-2021/12/18","曜日・時限":"集中","授業形態":"実技","単位数":"6.0","履修条件":"特になし","授業概要・カリキュラム上の位置づけ":"目的 卒業制作内容 テキスタイルの芸術性、生産性を視野に入れ4年間のまとめとして、各自の考えに基づいた新鮮な表現を作品、プレゼンテーションにより提案する。 領域の明確化は、制作をすすめている上で重要である。また作品のクオリティーを裏打ちする技法と素材の研究は多くの試作を重ねながら研究する。","到達目標":"作品としての密度をプロダクト、アートの両面から考察する。","ディプロマポリシーとの関連":"https://www.musabi.ac.jp/wp-content/uploads/2021/05/CurriculumMap_iic.pdf","授業計画・課題に対するフィードバック":"第 1 週 オリエンテーション テーマを各自設定して、レポート・プランを次週発表に備える。第 2 週 テーマの発表とディスカッション 講義・ドローイング・サンプル提示第 3 週 第1回中間発表第 4 週 第2回中間発表第 5 週 制作第 6 週 制作第 7 週 制作第 8 週 発表講評","準備学習内容・時間の目安":"特になし","成績評価の方法":"作品、プレゼンテーション、レポートを通して、オリジナル性、造形性などを重視し授業参加度と学習意欲、出席点の総合評価。","参考文献(作品）等":"プリントを適宜配付。"}