{"科目名":"健康と身体運動文化　Ⅴ","講義名":"健康と身体運動文化ⅤＢ（スポーツ映像論）","受講可能学科":"全学部・全学科","担当研究室":"身体運動文化","担当教員":"鬼丸　正明","分野":"文化総合Ⅰ類","対象学年":"1年、2年、3年、4年","科目群":"身体文化Ⅰ類","キャンパス":"鷹の台","開講期間":"後期 2021/09/06-2021/12/18","曜日・時限":"水３","授業形態":"講義","単位数":"2.0","履修条件":"150名","授業概要・カリキュラム上の位置づけ":"本講義では「運動としての映像」という視点から、映像技術・ジャンルを見直し、スポーツ映像の本質を探究する。","授業方法":"オンラインでの講義形式","到達目標":"映像の基礎的理解の上に、スポーツ映像を運動として理解する。","ディプロマポリシーとの関連":"https://www.musabi.ac.jp/wp-content/uploads/2021/05/CurriculumMap_la1.pdf","授業計画・課題に対するフィードバック":"第1回　オリエンテーション　運動としての映像第２～６回　映像技術論　フレーム・移動撮影・編集・特殊効果・音響効果第７～11回　映像ジャンル論　スラップスティック・ミュージカル・活劇・ドキュメンタリー第12～14回　スポーツ映像の過去・現在・未来","履修上の留意点":"講師は発話に障害があるので、人口音声を用いて授業を行う。","準備学習内容・時間の目安":"特になし。","成績評価の方法":"平常点。受講者には授業終了時に毎回小レポートを提出してもらう。評価はレポート提出回数と小レポートの内容を総合して行う。","テキスト":"なし","参考文献(作品）等":"なし","教員との連絡方法（オフィスアワー）":"質問等は、授業時間内に受け付ける。"}