{"科目名":"絵画実習Ⅶ","講義名":"絵画実習Ⅶ（日）","サブタイトル":"1～4授業週","受講可能学科":"造形学部・日本画学科","担当研究室":"日本画学科","担当教員":"尾長　良範、西田　俊英、岩田　壮平、間島　秀徳、浅見　貴子、橋本　晶子","分野":"専門Ⅰ類","対象学年":"4年","科目群":"専門Ⅰ類（必修）","キャンパス":"鷹の台","開講期間":"１.２期 2021/04/12-2021/06/05","曜日・時限":"集中","授業形態":"実技","単位数":"2.0","履修条件":"特になし","授業概要・カリキュラム上の位置づけ":"４年生、最初の授業として自主制作に取り組みます。自主制作では「何を、どのように、表現するのか」が問われますが優れた作家も最初から明快なコンセプトがあった訳ではありません。題材のデッサンや身体的なドローイングを繰り返す中から意識するようになったり、コンセプトとなるものがあっても試行錯誤しながら描くなかで変化してより強度を持ったコンセプトを得ることになったり、作家によってそのプロセスは様々です。卒業年度、最初の課題として各自の主題を深め、制作していきます。","授業方法":"オンラインと対面を併用","到達目標":"1　自己の表現として問うことができる主題を選び描くことができる。2　自己の表現について論理的にプレゼンテーションすることを実践、修得する。3　歴史や社会との関わりの中で自己の表現の意味を考え制作を行い、制作への意識を修得する。","ディプロマポリシーとの関連":"https://www.musabi.ac.jp/wp-content/uploads/2021/05/CurriculumMap_jp.pdf","授業計画・課題に対するフィードバック":"自主制作","履修上の留意点":"特になし","準備学習内容・時間の目安":"画集、文献、webなどを用い、現代・過去を問わず様々な芸術作品を観て研究しておくこと。図録などの解説文の内容を通読しておく。（120分）","成績評価の方法":"制作意図の論理性、作品の独自性、表現力を重視し実施するオンライン授業などへの参加状況を含めて総合的に評価する。"}