{"科目名":"考古学Ⅰ","講義名":"考古学ⅠA","サブタイトル":"日本考古学の魅力","受講可能学科":"全学部・全学科","担当研究室":"教養文化・学芸員","担当教員":"浅見　恵理","分野":"文化総合Ⅰ類","対象学年":"1年,2年,3年,4年","科目群":"教養文化Ⅰ類","キャンパス":"鷹の台","開講期間":"前期 2021/04/12-2021/07/10","曜日・時限":"火２","授業形態":"講義","単位数":"2.0","履修条件":"150人","授業概要・カリキュラム上の位置づけ":"発掘調査の実務経験を持つ教員が、日本考古学の理論と方法論について講義する。時代を追って、旧石器時代から縄文、弥生時代を経て、古墳時代に製作された考古遺物に見られる文様や製作技法について解説する。また、自然科学分析による石器や土器の産地同定の方法や、金属器の成分分析から分かることについても解説する。日本各地の博物館の展示や博物館活動などの様子を概観し、文化遺産としての保護と利用について理解を深める。","授業方法":"リアルタイム（同時双方向）：Zoomによるオンライン授業を行います。","到達目標":"①考古学の基本的な理論と方法論について理解することができる。②日本考古学の基礎知識について、理解し説明することができる。③様々な考古遺物にみられる文様の解釈や製作技法の成り立ちについて理解することができる。","ディプロマポリシーとの関連":"https://www.musabi.ac.jp/wp-content/uploads/2021/05/CurriculumMap_la1.pdf","授業計画・課題に対するフィードバック":"Zoomを用いて、教員と学生全員がオンラインで授業を実施します。内容の確認や意見交換を行うとともに、質疑応答なども授業中に対応する予定です。第1回　日本考古学の始まり　岩宿遺跡と旧石器第2回　縄文土器　縄の不思議第3回　縄文　土偶第4回　弥生土器第5回　弥生　青銅器（銅鐸絵画）第6回　前方後円墳の規格性第7回　装飾古墳の世界第8回　古鏡の謎第9回　副葬品第10回　金工技術の伝来　第11回　埴輪の意味第12回　埴輪の生産と流通第13回　考古遺物の自然科学分析第14回　文化遺産としての保護と活用第15回　日本考古学のまとめ・順番は変更になる可能性があります。・課題については授業中に指示します。","履修上の留意点":"Zoomを使用して授業を行います。使い方は事前に確認しておいてください。課題の提出はMicrosoft Teamsを使います。レジュメや資料をパワポで映し出しますので、できればパソコンで授業に参加するのが望ましいです。","準備学習内容・時間の目安":"考古遺物や文化財に関するニュースや本を読んだり、興味のあることについて調べたりして予備知識を得ておくこと。（30分）","成績評価の方法":"毎回の課題提出（出席確認）と期末レポートで評価します。","教員との連絡方法（オフィスアワー）":"講義内容に関する質問等は、毎授業時に受け付けます。"}