{"科目名":"プログラミングⅠ","講義名":"プログラミングⅠ","受講可能学科":"造形学部・デザイン情報学科","担当研究室":"デザイン情報学科","担当教員":"井上　尚司","分野":"専門Ⅱ類選択","対象学年":"2年,3年,4年","科目群":"専門Ⅱ類（選択）","キャンパス":"鷹の台","開講期間":"４期 2021/09/06-2021/10/02","曜日・時限":"火３,火４","授業形態":"演習","単位数":"2.0","履修条件":"「プログラミングⅠ」と「プログラミングⅡ」を連続して履修すること。","授業概要・カリキュラム上の位置づけ":"この授業では、コンピュータのプログラミングを基礎から学ぶ。利用するのは、初心者でも理解しやすく、ウェブシステムでの利用もできる言語とし、汎用的にも利用できるPerlを中心に学習する。授業では、それに加えてJavaScriptの基本も学習し、演習を行う。基本的な主題は「データ構造＋アルゴリズム＝プログラム」である。プログラムを作る際に必要となるデータ構造とアルゴリズムそれぞれについて学び、それらを総合してある有用な機能を持ったプログラムの作成を試みる。最終的に簡単なプログラムならすぐに作れるようになることを目標とする。","授業方法":"演習の内容から、授業はすべて対面で行う。","到達目標":"(1) プログラミング言語のPerlを使って、簡単なプログラムを作れるようになること。(2) JavaScriptの基礎的な知識を習得し、簡単なプログラムを作れるようになること。","ディプロマポリシーとの関連":"https://www.musabi.ac.jp/wp-content/uploads/2021/05/CurriculumMap_di.pdf","授業計画・課題に対するフィードバック":"Perlを使って以下の項目を学習する。・順次、繰り返し、選択などのアルゴリズムの基本・数値型、文字型、論理型などの基本データ形式・配列型・CGIのしくみ、使い方・CGI/Perlを使った自由課題JavaScriptの基本を学習する。","履修上の留意点":"教職免許状（高等学校教諭第1種〈情報〉）を取得するための科目。","準備学習内容・時間の目安":"特になし","成績評価の方法":"出席、受講態度、課題等の総合評価とする。課題数は多く、全部で30程度となる。ひとつひとつは小さなプログラムではあるが、すべて提出することが求められる。","テキスト":"最低限の情報については、プリントを配付して対応する。","参考文献(作品）等":"各自の理解度に応じて、HTML、Perl、JavaScriptの書籍を用意するとよい。他に、CGIやUNIXの書籍があることが望ましい。推奨書籍は適宜示す。"}