{"科目名":"初級イタリア語　１－２","講義名":"初級イタリア語１－２Ｂ","サブタイトル":"文法講読","受講可能学科":"全学部・全学科","担当研究室":"言語文化","担当教員":"高田　和広","分野":"文化総合Ⅱ類","対象学年":"1年,2年,3年,4年","科目群":"言語文化Ⅱ類","キャンパス":"鷹の台","開講期間":"後期 2021/09/06-2021/12/18","曜日・時限":"土５","授業形態":"演習","単位数":"2.0","履修条件":"この科目を履修するためには、前期開設の「初級イタリア語1－1B」もあわせて履修しなければなりません。なお、前年度までに上記の前期開設科目の単位を既に修得した者は、この科目を履修することはできません。","授業概要・カリキュラム上の位置づけ":"「初級イタリア語1−1A・B」の続きです。同じ要領で授業を進めます。","授業方法":"リアルタイム（同時双方向）： Zoomによるオンライン授業を行います。","到達目標":"①基礎文法を理解し、イタリア語ならではの特徴や決まりを習得する。②学習事項を使って相手に簡単な質問をしたり自分の事を説明したりできる。③辞書やヒントの助けを借りて、短い文章を読み解くことができる。","ディプロマポリシーとの関連":"https://www.musabi.ac.jp/wp-content/uploads/2021/05/CurriculumMap_la2.pdf","授業計画・課題に対するフィードバック":"Zoomを用いて、教員と学生全員がオンラインで授業を実施します。授業内で時間を設けて質疑応答にも対応します。第1回 前期のおさらい  第2回 unità4 自分の年齢を言おう（数字と動詞avere）第3回 unità4 お腹がすいています（動詞avereと慣用表現）第4回 unità5 規則動詞Ⅰ -are（自己紹介）  第5回 unità5 規則動詞Ⅱ -ere（レストランで注文）第6回 unità5 規則動詞Ⅲ -ire（旅行の計画）第7回 unità5 規則動詞Ⅳ -isc（好みを説明する）第8回 unità5 まとめと練習問題第9回 unità6 不規則動詞Ⅰ（週末の予定）　　 第10回 unità6 不規則動詞Ⅱ（週末の予定）第11回 unità6 不規則動詞Ⅲ（来る、出かける）第12回 unità6 助動詞Ⅰ（～したい、～できる）  第13回 unità6 助動詞Ⅱ（～ないといけない）第14回 unità6 助動詞Ⅲ（料理ができる） 第15回 unità6 まとめと練習問題","履修上の留意点":"毎回Ｚoomを使用して授業を行います。ほぼ毎回発言を求めますので、受講者はマイク機能が必要となります。パワーポイントと音声を画面共有しながら授業を進めていきますので、できればノートパソコンで授業に参加するのが望ましいです。授業開始までにログインを済ませておいてください。授業当日に出欠を取り、参加を確認します。なお、オンラインでの学習をより円滑に進めるため、教科書の他、必要に応じて補助プリントを使用する場合があります。補助プリントは事前にTeamsに掲示します。","準備学習内容・時間の目安":"予習の必要はありませんが、代わりに学んだ事柄をなるべく復習するようにしてください。自宅で復習できるよう「自習用練習問題（解答付き）」を配布します。準備学習時間60分。","成績評価の方法":"平常点（出席・小テスト）40％、オンラインでの学期末試験60％で総合的に評価。","テキスト":"書名『イタリアーノ・アル・ボーロ！』、近藤直樹／カパッソ・カロリーナ著、朝日出版社","テキストISBN番号":"ISBN: 978-4-255-55316-0","参考文献(作品）等":"なし","教員との連絡方法（オフィスアワー）":"講義内容に関する質問等は、毎授業時に受け付けます。"}