{"科目名":"クラフトデザインⅤ","講義名":"クラフトデザインⅤ","サブタイトル":"クラフトデザインⅤ［3年］木工（収納家具の制作）8〜13授業週 〈3単位 実技〉十時啓悦","受講可能学科":"造形学部・工芸工業デザイン学科","担当研究室":"工芸工業デザイン学科","担当教員":"北川　八十治、藤井　常雄、宗像　重幸","分野":"専門Ⅰ類","対象学年":"3年","科目群":"専門Ⅰ類（選択）","キャンパス":"鷹の台","開講期間":"２.３期 2021/05/10-2021/07/03","曜日・時限":"集中","授業形態":"実技","単位数":"3.0","履修条件":"特になし","授業概要・カリキュラム上の位置づけ":"＊「クラフトデザインⅣ」でデザインした収納家具を制作する。＊ 収納家具の各パーツの名称と構造、作り方、金物の研究および使用方法を学ぶ。・条件 大きさは高さ、幅、奥行きの合計（収納部の合計）が1800mm 以内であること。扉、引き出し等付けるのは構わないが、引き出しの場合に限り三個以内とする。サイドボード、カップボード、整理ダンス、各種棚など包みかくすものであること。","授業方法":"状況によりオンライン授業で実施することがあります。それに伴い、授業日程や内容が変更になることがあります。","到達目標":"箱構造と機能を理解し、収納家具のデザイン、構造を学ぶ。","ディプロマポリシーとの関連":"https://www.musabi.ac.jp/wp-content/uploads/2021/05/CurriculumMap_iic.pdf","授業計画・課題に対するフィードバック":"第１週～第２週 制作にあたっての心構え説明。前課題のレンダリングをもとに、1/5 モデル、1/5 図面、原寸図面と進めていき、その都度チェック、修正を加えながら、制作原寸図を仕上げる。第３週～第５週 各自で木材を購入し、木取り図制作。大型機械の説明をして実際に制作していく。第６週 細部に手間をかけ仕上げる。 講評","履修上の留意点":"最終的にできた作品と、それまでのプロセスに重点を置いて評価する。使用する木材を事前にリサーチしデザインを進めること。","準備学習内容・時間の目安":"前回のアイデアスケッチから現物作品までのプロセスを学ぶ。","成績評価の方法":"提出作品すべて、出席日数、作品完成までのプロセス。提出物（現物作品、原寸図青焼、プレゼンテーションボード）","テキスト":"作成したプリントを配付。"}