[[{"0":"科目名","1":"初級日本語　１－５","2":"講義名","3":"初級日本語１－５"},{"0":"サブタイトル","1":"文法"},{"0":"受講可能学科","1":"全学部・全学科"},{"0":"担当研究室","1":"言語文化"},{"0":"担当教員","1":"佐藤　正則"},{"0":"分野","1":"文化総合Ⅱ類","2":"対象学年","3":"1年,2年,3年,4年"},{"0":"科目群","1":"言語文化Ⅱ類","2":"キャンパス","3":"鷹の台"},{"0":"開講期間","1":"前期 2021/04/12-2021/07/10","2":"曜日・時限","3":"月３"},{"0":"授業形態","1":"演習","2":"単位数","3":"2.0"},{"0":"履修条件","1":"外国人留学生のみ履修可。中級・上級日本語の単位を取得済みの場合は履修不可。プレイスメント試験の結果に応じて、自動で履修登録される。"},{"0":"授業概要・カリキュラム上の位置づけ","1":"テキストを使用し、読むため、書くための文法、言葉を学習する。"},{"0":"授業方法","1":"リアルタイム（ZOOM使用)で授業を行います。Teamsを使用し課題の提出等を行います。テキストの文法事項を、問題演習によって理解度を確認しながら、進めていきます。"},{"0":"到達目標","1":"読むため、書くために必要な文法を理解し、使うことができる。"},{"0":"ディプロマポリシーとの関連","1":"https://www.musabi.ac.jp/wp-content/uploads/2021/05/CurriculumMap_la2.pdf"},{"0":"授業計画・課題に対するフィードバック","1":"第1回  　オリエンテーション第2回  　書き言葉の文体第3回  　連用中止形第4回  　文の構造第5回  　「こと」第6回  　助詞相当語第7回  　指示語第8回  　従属節①　第9回  　従属節②第10回  　接続表現①第11回  　前回までの復習①第12回  　前回までの復習②第13回  　まとめ準備①第14回  　まとめ準備②第15回  　まとめ"},{"0":"履修上の留意点","1":"Ｚoomを使用して授業を行います。使い方は事前に確認しておいてください．Teamsを通して、事前に資料を配付します。課題の提出方法は、授業で指示します。レジュメや資料をスクリーンにも映しだしますので、できればノートパソコンで授業に参加するのが望ましいです。授業開始10分前までに、ログインしておくこと。出欠確認として、当日の参加を確認します。ほぼ毎回、発言を求めます。"},{"0":"準備学習内容・時間の目安","1":"授業で学んだ文型は復習しておくこと（30分）"},{"0":"成績評価の方法","1":"オンラインでの期末試験、提出物、授業参加度の総合で評価します。"},{"0":"テキスト","1":"『改定版　大学・大学院　留学生の日本語　①読解編』アカデミック・ジャパニーズ研究会編著、アルク出版　履修が確定した学生は、世界堂の店頭でテキストを各自購入してください。在庫不足の場合は、ISBN番号を参考にし、書店や出版社から各自購入してください。"},{"0":"テキストISBN番号","1":"978-4-7574-2631-3"},{"0":"参考文献(作品）等","1":"なし"},{"0":"教員との連絡方法（オフィスアワー）","1":"講義内容に関する質問等は、毎授業時に受け付ける。"}]]