[[{"0":"科目名","1":"健康と身体運動文化　９１","2":"講義名","3":"健康と身体運動文化９１（テニス）"},{"0":"受講可能学科","1":"全学部・全学科"},{"0":"担当研究室","1":"身体運動文化"},{"0":"担当教員","1":"青沼　裕之"},{"0":"分野","1":"文化総合Ⅱ類","2":"対象学年","3":"1年,2年,3年,4年"},{"0":"科目群","1":"身体文化Ⅱ類","2":"キャンパス","3":"鷹の台"},{"0":"開講期間","1":"前期 2021/04/12-2021/07/10","2":"曜日・時限","3":"火４"},{"0":"授業形態","1":"実技（身体）","2":"単位数","3":"1.0"},{"0":"履修条件","1":"特になし"},{"0":"授業概要・カリキュラム上の位置づけ","1":"このテニスの授業は、グループ・ノートを活用するグループ学習によって、学生自身が授業へ自主的、計画的に参加することが前提となっている。教師からの一方的な伝達と指示によって技術習得がなされていくような授業ではなく、学習者自らが技術を学び取っていく授業にしたい。技術学習の系統、練習方法、自己の技能やその習得過程に対する認識を大事にしたい。同時に、そうした認識を自己の内にとどめず、交流し合い、互いに確認してほしい。ダブルスのゲームが楽しめるようにすることを最終目標とするが、そのためにストローク、ボレー、ロブ、サーブ、スマッシュの打ち方・打点・タイミングの習得とともに、コースや高さの打ち分け、ゲームの駆け引きについて理解する。"},{"0":"授業方法","1":"グループ学習をおこなう。ただし、新型コロナウイルス感染症への対策として作成したガイドラインに沿って授業をおこなう。※この授業は、大学内の施設を利用した「対面授業」です。詳細は第１回目の授業で説明します。"},{"0":"到達目標","1":"ストローク、ボレー、ロブ、サーブ、スマッシュの打ち方・打点・タイミング、コースや高さの打ち分け、前衛と後衛の役割分担、ゲームの戦術を理解する。"},{"0":"ディプロマポリシーとの関連","1":"https://www.musabi.ac.jp/wp-content/uploads/2021/05/CurriculumMap_la2.pdf"},{"0":"授業計画・課題に対するフィードバック","1":"第1回（講義①） 学習計画の確認、リーダー・係・グループ名の決定第2回 グリップ、コート等の説明、ボールを面で捉える練習第3回～第4回　グランドストローク(フォアハンドとバックハンド)、ロブ、サービス第5回～第6回　ボレー(フォアハンドとバックハンド)、サービス、種マッシュ第7回～第11回　班ごとに課題を持って、練習内容を決めて実行第12回～第14回　ダブルスの班対抗戦第15回　学習のまとめ＊第4回からは、各グループで練習計画を立てる。"},{"0":"履修上の留意点","1":"初心者歓迎。練習・ゲームでは、楽しき中にも知恵と工夫を盛り込んでほしい。原則としてテニスシューズ(オムニ・クレーコート用)を履いてくること。夏場は帽子着用、タオル・飲料水持参。"},{"0":"準備学習内容・時間の目安","1":"グループで自主的な学習を進めていく関係上、事前に次回の練習計画を立て、グループ・ノートに記録し提出する。"},{"0":"成績評価の方法","1":"全授業数の75％以上の出席者を評価の対象とする。出席点を50％、レポート点を30％、グループノートの作成と学習への取り組み方を20％として評価する。"},{"0":"テキスト","1":"授業時に資料を配付する。"},{"0":"テキストISBN番号","1":"なし。"},{"0":"参考文献(作品）等","1":"参考書や解説書は図書館に所蔵されているので、各人それを利用する。NETの資料も活用する。バリエーションある練習方法、攻守の技術・戦術等をそこから学ぶ。"},{"0":"教員との連絡方法（オフィスアワー）","1":"オフィスアワーで対応する。青沼のメール（h-aonuma@musabi.ac.jp ）でも対応する。"}]]